oxygent/__init__.py
oxygent/banner.py
oxygent/config.py
oxygent/core_tools/__init__.py
oxygent/core_tools/retrieve_tools.py
oxygent/databases/__init__.py
oxygent/databases/base_db.py
oxygent/databases/db_es/__init__.py
oxygent/databases/db_es/base_es.py
oxygent/databases/db_es/jes_es.py
oxygent/databases/db_es/local_es.py
oxygent/databases/db_redis/__init__.py
oxygent/databases/db_redis/base_redis.py
oxygent/databases/db_redis/jimdb_ap_redis.py
oxygent/databases/db_redis/local_redis.py
oxygent/databases/db_vector/__init__.py
oxygent/databases/db_vector/base_vector_db.py
oxygent/databases/db_vector/vearch_db.py
oxygent/db_factory.py
oxygent/embedding_cache.py
oxygent/live_prompt/__init__.py
oxygent/live_prompt/manager.py
oxygent/live_prompt/wrapper.py
oxygent/log_setup.py
oxygent/mas.py
oxygent/oxy/__init__.py
oxygent/oxy/agents/__init__.py
oxygent/oxy/agents/base_agent.py
oxygent/oxy/agents/chat_agent.py
oxygent/oxy/agents/local_agent.py
oxygent/oxy/agents/parallel_agent.py
oxygent/oxy/agents/rag_agent.py
oxygent/oxy/agents/react_agent.py
oxygent/oxy/agents/remote_agent.py
oxygent/oxy/agents/sse_oxy_agent.py
oxygent/oxy/agents/workflow_agent.py
oxygent/oxy/api_tools/__init__.py
oxygent/oxy/api_tools/http_tool.py
oxygent/oxy/bank_tools/__init__.py
oxygent/oxy/bank_tools/bank_client.py
oxygent/oxy/bank_tools/bank_tool.py
oxygent/oxy/bank_tools/base_bank.py
oxygent/oxy/base_flow.py
oxygent/oxy/base_oxy.py
oxygent/oxy/base_tool.py
oxygent/oxy/flows/__init__.py
oxygent/oxy/flows/parallel_flow.py
oxygent/oxy/flows/plan_and_solve.py
oxygent/oxy/flows/reflexion.py
oxygent/oxy/flows/workflow.py
oxygent/oxy/function_tools/__init__.py
oxygent/oxy/function_tools/function_hub.py
oxygent/oxy/function_tools/function_tool.py
oxygent/oxy/llms/__init__.py
oxygent/oxy/llms/base_llm.py
oxygent/oxy/llms/http_llm.py
oxygent/oxy/llms/local_llm.py
oxygent/oxy/llms/mock_llm.py
oxygent/oxy/llms/openai_llm.py
oxygent/oxy/llms/remote_llm.py
oxygent/oxy/mcp_tools/__init__.py
oxygent-1.0.10.dist-info/LICENSE
oxygent-1.0.10.dist-info/METADATA
oxygent-1.0.10.dist-info/NOTICE_Third_Party.md
oxygent-1.0.10.dist-info/WHEEL
oxygent-1.0.10.dist-info/RECORD
