Metadata-Version: 2.3
Name: oxygent
Version: 1.0.10
Summary: Multi-Agent Collaboration Framework
Author: jd-oxygen
Author-email: litianlong26@jd.com
Requires-Python: >=3.10,<4.0
Classifier: Programming Language :: Python :: 3
Classifier: Programming Language :: Python :: 3.10
Classifier: Programming Language :: Python :: 3.11
Classifier: Programming Language :: Python :: 3.12
Classifier: Programming Language :: Python :: 3.13
Requires-Dist: aiofiles
Requires-Dist: aiohttp
Requires-Dist: aiohttp-sse-client
Requires-Dist: aioredis
Requires-Dist: colorama
Requires-Dist: elasticsearch (==7.17.12)
Requires-Dist: fastapi
Requires-Dist: httpx
Requires-Dist: mcp
Requires-Dist: msgpack
Requires-Dist: numpy
Requires-Dist: openai
Requires-Dist: pandas
Requires-Dist: pillow
Requires-Dist: pydantic
Requires-Dist: python-multipart
Requires-Dist: requests
Requires-Dist: shortuuid
Requires-Dist: tqdm
Requires-Dist: uv
Requires-Dist: uvicorn
Requires-Dist: websockets
